doc/ltxobj/ladok3.pdf
ladok3/Makefile
ladok3/__init__.py
ladok3/api.nw
ladok3/cli.nw
ladok3/cli.py
ladok3/data.nw
ladok3/data.py
ladok3/ladok.bash
ladok3/ladok3.nw
ladok3/report.nw
ladok3/report.py
ladok3/scripts.nw
ladok3/student.nw
ladok3/student.py
ladok3/undoc.nw
ladok3-5.8.dist-info/METADATA
ladok3-5.8.dist-info/WHEEL
ladok3-5.8.dist-info/entry_points.txt
ladok3-5.8.dist-info/licenses/LICENSE
ladok3-5.8.dist-info/RECORD
