Metadata-Version: 2.4
Name: ladok3
Version: 5.8
Summary: Python wrapper and CLI for the LADOK3 REST API.
License-Expression: MIT
License-File: LICENSE
Keywords: ladok3,ladok
Author: Daniel Bosk
Author-email: daniel@bosk.se
Maintainer: Daniel Bosk
Maintainer-email: dbosk@kth.se
Requires-Python: >=3.8,<4.0
Classifier: Programming Language :: Python :: 3
Classifier: License :: OSI Approved :: MIT License
Classifier: Operating System :: OS Independent
Classifier: Environment :: Console
Classifier: Intended Audience :: Education
Classifier: Intended Audience :: Science/Research
Classifier: Topic :: Utilities
Requires-Dist: appdirs (>=1.4.4,<2.0.0)
Requires-Dist: argcomplete (>=2.0.0,<3.0.0)
Requires-Dist: cachetools (>=5.2.0,<6.0.0)
Requires-Dist: cryptography (>=41.0.3,<42.0.0)
Requires-Dist: keyring (>=24.2.0,<25.0.0)
Requires-Dist: requests (>=2.31.0,<3.0.0)
Requires-Dist: urllib3 (>=2.0)
Requires-Dist: weblogin (>=1.13,<2.0)
Project-URL: Bug Tracker, https://github.com/dbosk/ladok3/issues
Project-URL: Documentation, https://github.com/dbosk/ladok3/releases
Project-URL: Repository, https://github.com/dbosk/ladok3
